odoo8_addon_l10n_cn_fapiao-8.0.1.0.0.99.dev14-nspkg.pth
odoo_addons/l10n_cn_fapiao/README.rst
odoo_addons/l10n_cn_fapiao/__init__.py
odoo_addons/l10n_cn_fapiao/__openerp__.py
odoo_addons/l10n_cn_fapiao/data/fapiao_tax_type.xml
odoo_addons/l10n_cn_fapiao/demo/fapiao_demo.xml
odoo_addons/l10n_cn_fapiao/models/__init__.py
odoo_addons/l10n_cn_fapiao/models/account_invoice.py
odoo_addons/l10n_cn_fapiao/models/fapiao.py
odoo_addons/l10n_cn_fapiao/models/fapiao_tag.py
odoo_addons/l10n_cn_fapiao/models/fapiao_tax_type.py
odoo_addons/l10n_cn_fapiao/security/ir.model.access.csv
odoo_addons/l10n_cn_fapiao/static/description/icon.png
odoo_addons/l10n_cn_fapiao/static/description/index.html
odoo_addons/l10n_cn_fapiao/static/description/l10n_cn_fapiao1.png
odoo_addons/l10n_cn_fapiao/tests/__init__.py
odoo_addons/l10n_cn_fapiao/tests/test_fapiao.py
odoo_addons/l10n_cn_fapiao/views/fapiao_view.xml
odoo8_addon_l10n_cn_fapiao-8.0.1.0.0.99.dev14.dist-info/METADATA
odoo8_addon_l10n_cn_fapiao-8.0.1.0.0.99.dev14.dist-info/WHEEL
odoo8_addon_l10n_cn_fapiao-8.0.1.0.0.99.dev14.dist-info/namespace_packages.txt
odoo8_addon_l10n_cn_fapiao-8.0.1.0.0.99.dev14.dist-info/top_level.txt
odoo8_addon_l10n_cn_fapiao-8.0.1.0.0.99.dev14.dist-info/RECORD
